update_dotdee/__init__.py
update_dotdee/cli.py
update_dotdee/tests.py
update_dotdee-6.0.dist-info/LICENSE.txt
update_dotdee-6.0.dist-info/METADATA
update_dotdee-6.0.dist-info/WHEEL
update_dotdee-6.0.dist-info/entry_points.txt
update_dotdee-6.0.dist-info/top_level.txt
update_dotdee-6.0.dist-info/RECORD
